cerb_code/Dockerfile
cerb_code/__init__.py
cerb_code/launch.sh
cerb_code/backend/__init__.py
cerb_code/backend/mcp_server.py
cerb_code/backend/monitor.py
cerb_code/frontend/__init__.py
cerb_code/frontend/app.py
cerb_code/frontend/state.py
cerb_code/frontend/widgets/__init__.py
cerb_code/frontend/widgets/diff_tab.py
cerb_code/frontend/widgets/hud.py
cerb_code/frontend/widgets/monitor_tab.py
cerb_code/lib/__init__.py
cerb_code/lib/agent_protocol.py
cerb_code/lib/config.py
cerb_code/lib/file_watcher.py
cerb_code/lib/helpers.py
cerb_code/lib/logger.py
cerb_code/lib/monitor.py
cerb_code/lib/prompts.py
cerb_code/lib/sessions.py
cerb_code/lib/tmux_agent.py
cerb_code/runners/__init__.py
cerb_code/runners/cerb-hook-forward.sh
cerb_code/runners/cerb_launcher.py
cerb_code/runners/hook_monitor.py
cerb_code/runners/kerberos.py
cerb_code-0.1.19.dist-info/METADATA
cerb_code-0.1.19.dist-info/WHEEL
cerb_code-0.1.19.dist-info/entry_points.txt
cerb_code-0.1.19.dist-info/top_level.txt
cerb_code-0.1.19.dist-info/RECORD
